{
    "key": "group_64a8791d77739",
    "title": "Bloc accompagnement pour page Accueil",
    "fields": [
        {
            "key": "field_64a8791d7f0e2",
            "label": "Bloc accompagnement pour page Accueil",
            "name": "",
            "aria-label": "",
            "type": "message",
            "instructions": "",
            "required": 0,
            "conditional_logic": 0,
            "wrapper": {
                "width": "",
                "class": "",
                "id": ""
            },
            "message": "Section avec titre, intro, services avec pictos sur 3 colonnes et bouton. Affichage simplifié en mobile.",
            "new_lines": "wpautop",
            "esc_html": 0
        },
        {
            "key": "field_64a8791d82b78",
            "label": "Titre de la section",
            "name": "titre_section",
            "aria-label": "",
            "type": "textarea",
            "instructions": "Les mots entre balises span seront affichés en rose",
            "required": 0,
            "conditional_logic": 0,
            "wrapper": {
                "width": "",
                "class": "",
                "id": ""
            },
            "default_value": "",
            "maxlength": "",
            "rows": 1,
            "placeholder": "",
            "new_lines": "br"
        },
        {
            "key": "field_64a8794aaa8d4",
            "label": "Introduction de la section",
            "name": "intro_section",
            "aria-label": "",
            "type": "textarea",
            "instructions": "",
            "required": 0,
            "conditional_logic": 0,
            "wrapper": {
                "width": "",
                "class": "",
                "id": ""
            },
            "default_value": "",
            "maxlength": "",
            "rows": 4,
            "placeholder": "",
            "new_lines": "br"
        },
        {
            "key": "field_64a8791d8682d",
            "label": "Prestations",
            "name": "services",
            "aria-label": "",
            "type": "repeater",
            "instructions": "",
            "required": 1,
            "conditional_logic": 0,
            "wrapper": {
                "width": "",
                "class": "",
                "id": ""
            },
            "layout": "row",
            "pagination": 0,
            "min": 1,
            "max": 0,
            "collapsed": "",
            "button_label": "Ajouter un service",
            "rows_per_page": 20,
            "sub_fields": [
                {
                    "key": "field_64d0c603465f5",
                    "label": "Titre",
                    "name": "titre",
                    "aria-label": "",
                    "type": "textarea",
                    "instructions": "",
                    "required": 0,
                    "conditional_logic": 0,
                    "wrapper": {
                        "width": "",
                        "class": "",
                        "id": ""
                    },
                    "default_value": "",
                    "maxlength": "",
                    "rows": 2,
                    "placeholder": "",
                    "new_lines": "br",
                    "parent_repeater": "field_64a8791d8682d"
                },
                {
                    "key": "field_64d0c60b465f6",
                    "label": "Picto",
                    "name": "picto",
                    "aria-label": "",
                    "type": "image",
                    "instructions": "SVG ou PNG noir sur fond transparent",
                    "required": 0,
                    "conditional_logic": 0,
                    "wrapper": {
                        "width": "",
                        "class": "",
                        "id": ""
                    },
                    "return_format": "id",
                    "library": "all",
                    "min_width": "",
                    "min_height": "",
                    "min_size": "",
                    "max_width": "",
                    "max_height": "",
                    "max_size": "",
                    "mime_types": "svg,png",
                    "preview_size": "medium",
                    "parent_repeater": "field_64a8791d8682d"
                },
                {
                    "key": "field_64d0c61c465f7",
                    "label": "Chiffre",
                    "name": "chiffre",
                    "aria-label": "",
                    "type": "text",
                    "instructions": "",
                    "required": 0,
                    "conditional_logic": 0,
                    "wrapper": {
                        "width": "",
                        "class": "",
                        "id": ""
                    },
                    "default_value": "",
                    "maxlength": "",
                    "placeholder": "",
                    "prepend": "",
                    "append": "",
                    "parent_repeater": "field_64a8791d8682d"
                },
                {
                    "key": "field_64d0c62a465f8",
                    "label": "Texte",
                    "name": "texte",
                    "aria-label": "",
                    "type": "textarea",
                    "instructions": "",
                    "required": 0,
                    "conditional_logic": 0,
                    "wrapper": {
                        "width": "",
                        "class": "",
                        "id": ""
                    },
                    "default_value": "",
                    "maxlength": "",
                    "rows": 2,
                    "placeholder": "",
                    "new_lines": "br",
                    "parent_repeater": "field_64a8791d8682d"
                }
            ]
        },
        {
            "key": "field_64d0c66d2daaa",
            "label": "Bouton",
            "name": "lien",
            "aria-label": "",
            "type": "link",
            "instructions": "",
            "required": 0,
            "conditional_logic": 0,
            "wrapper": {
                "width": "",
                "class": "",
                "id": ""
            },
            "return_format": "array"
        }
    ],
    "location": [
        [
            {
                "param": "block",
                "operator": "==",
                "value": "acf\/accueil-accompagnement"
            }
        ]
    ],
    "menu_order": 0,
    "position": "normal",
    "style": "default",
    "label_placement": "top",
    "instruction_placement": "label",
    "hide_on_screen": "",
    "active": true,
    "description": "",
    "show_in_rest": 0,
    "modified": 1691404144
}
